swapanything/__about__.py
swapanything/__init__.py
swapanything/prep.py
swapanything/select.py
swapanything_backend/__init__.py
swapanything_backend/_base.py
swapanything_backend/airtable.py
swap_anything-0.2.0.dist-info/LICENSE
swap_anything-0.2.0.dist-info/METADATA
swap_anything-0.2.0.dist-info/WHEEL
swap_anything-0.2.0.dist-info/top_level.txt
swap_anything-0.2.0.dist-info/RECORD
