Metadata-Version: 2.1
Name: swap-anything
Version: 0.2.0
Summary: A mix and match (swap) library to empower swapping-based projects.
Author: @CheckSim, @LFK01
Author-email: "@ggbaro" <46573388+ggbaro@users.noreply.github.com>
Maintainer-email: "@ggbaro" <46573388+ggbaro@users.noreply.github.com>
License: MIT License
Classifier: Development Status :: 4 - Beta
Classifier: Intended Audience :: Developers
Classifier: Intended Audience :: Education
Classifier: Intended Audience :: Information Technology
Classifier: Intended Audience :: Science/Research
Classifier: License :: OSI Approved :: MIT License
Classifier: Operating System :: OS Independent
Classifier: Programming Language :: Python
Classifier: Programming Language :: Python :: 3
Classifier: Programming Language :: Python :: 3 :: Only
Classifier: Programming Language :: Python :: 3.10
Classifier: Programming Language :: Python :: 3.11
Classifier: Programming Language :: Python :: 3.12
Classifier: Topic :: Internet
Classifier: Topic :: Software Development :: Libraries
Classifier: Topic :: Software Development :: Libraries :: Application Frameworks
Classifier: Topic :: Software Development :: Libraries :: Python Modules
Classifier: Topic :: Software Development
Classifier: Topic :: Utilities
Classifier: Typing :: Typed
Requires-Python: <3.13,>=3.10
License-File: LICENSE
Requires-Dist: pandas <3,>=1.5
Requires-Dist: networkx <3.2,>=3.1
Requires-Dist: numpy <2,>=1.21.0
Provides-Extra: airtable
Requires-Dist: pyairtable <1.6,>=1.5.0 ; extra == 'airtable'
Requires-Dist: pydantic <3,>=2 ; extra == 'airtable'
Requires-Dist: pydantic-settings ; extra == 'airtable'
Provides-Extra: all
Requires-Dist: pyairtable <1.6,>=1.5.0 ; extra == 'all'
Requires-Dist: pydantic <3,>=2 ; extra == 'all'
Requires-Dist: pydantic-settings ; extra == 'all'
Provides-Extra: backend
Requires-Dist: pydantic <3,>=2 ; extra == 'backend'
Requires-Dist: pydantic-settings ; extra == 'backend'
Provides-Extra: dev
Requires-Dist: black ; extra == 'dev'
Requires-Dist: ruff ; extra == 'dev'
Requires-Dist: pre-commit ; extra == 'dev'
Requires-Dist: setuptools-scm ; extra == 'dev'
Provides-Extra: docs
Requires-Dist: mkdocs ; extra == 'docs'
Requires-Dist: mkdocs-material ; extra == 'docs'
Requires-Dist: mkdocstrings ; extra == 'docs'
Requires-Dist: mkdocs-jupyter ; extra == 'docs'
Requires-Dist: mkdocstrings[python] ; extra == 'docs'
Requires-Dist: pytkdocs[numpy-style] ; extra == 'docs'
Provides-Extra: test
Requires-Dist: requests ; extra == 'test'
Requires-Dist: pytest ; extra == 'test'
Requires-Dist: pytest-cov ; extra == 'test'
Requires-Dist: Faker ; extra == 'test'
